montage_wrapper/__init__.py
montage_wrapper/_astropy_init.py
montage_wrapper/commands.py
montage_wrapper/commands_extra.py
montage_wrapper/conftest.py
montage_wrapper/mpi.py
montage_wrapper/status.py
montage_wrapper/version.py
montage_wrapper/wrappers.py
montage_wrapper/tests/__init__.py
montage_wrapper/tests/coveragerc
montage_wrapper/tests/setup_package.py
montage_wrapper/tests/test_commands.py
montage_wrapper/tests/test_wrappers.py
montage_wrapper-0.9.9.dist-info/DESCRIPTION.rst
montage_wrapper-0.9.9.dist-info/METADATA
montage_wrapper-0.9.9.dist-info/RECORD
montage_wrapper-0.9.9.dist-info/WHEEL
montage_wrapper-0.9.9.dist-info/metadata.json
montage_wrapper-0.9.9.dist-info/top_level.txt
